README.rst
setup.py
rest_framework_pagination/__init__.py
rest_framework_pagination/pagination.py
rest_framework_pagination.egg-info/PKG-INFO
rest_framework_pagination.egg-info/SOURCES.txt
rest_framework_pagination.egg-info/dependency_links.txt
rest_framework_pagination.egg-info/requires.txt
rest_framework_pagination.egg-info/top_level.txt