Metadata-Version: 1.2
Name: rest_framework_pagination
Version: 0.0.1
Summary: Django REST framework limit/offset pagination with multiple queryset support
Home-page: https://github.com/imzaur/drf_multi_queryset_pagination
Author: Zaur Magamednebiev
Author-email: imzaur777@gmail.com
License: MIT
Platform: UNKNOWN
Requires-Python: >=3.6
